github_tools/__init__.py
github_tools/gh_create_milestone.py
github_tools/gh_issue_templates.py
github_tools/gh_repos.py
github_tools/github_issue_templates.py
github_tools/github_tools_examples.py
ops_py_github_tools-1.1.5.dist-info/LICENSE
ops_py_github_tools-1.1.5.dist-info/METADATA
ops_py_github_tools-1.1.5.dist-info/WHEEL
ops_py_github_tools-1.1.5.dist-info/top_level.txt
ops_py_github_tools-1.1.5.dist-info/RECORD
