Metadata-Version: 2.1
Name: ops-py-github-tools
Version: 1.1.5
Summary: Selection of tools to use with GitHub
License: MIT License
License-File: LICENSE
Requires-Dist: certifi ==2024.8.30
Requires-Dist: charset-normalizer ==3.4.0
Requires-Dist: idna ==3.10
Requires-Dist: pip ==24.3.1
Requires-Dist: requests ==2.32.3
Requires-Dist: setuptools ==75.5.0
Requires-Dist: urllib3 ==2.2.3
